regression_model/VERSION
regression_model/__init__.py
regression_model/config.yml
regression_model/pipeline.py
regression_model/predict.py
regression_model/train_pipeline.py
regression_model/config/__init__.py
regression_model/config/core.py
regression_model/datasets/__init__.py
regression_model/datasets/dft_calc_test.csv
regression_model/datasets/dft_calc_test_validation.csv
regression_model/datasets/dft_calc_train.csv
regression_model/datasets/elemental_properties.csv
regression_model/datasets/shannon_radius.csv
regression_model/processing/__init__.py
regression_model/processing/data_manager.py
regression_model/processing/features.py
regression_model/processing/validation.py
regression_model/trained_models/__init__.py
regression_model/trained_models/regression_model_output.pkl
stableperovskites-1.0.3.dist-info/LICENSE.txt
stableperovskites-1.0.3.dist-info/METADATA
stableperovskites-1.0.3.dist-info/WHEEL
stableperovskites-1.0.3.dist-info/top_level.txt
stableperovskites-1.0.3.dist-info/RECORD
